dict_util/__init__.py
dict_util/dict_util.py
dict_util-1.4.2.dist-info/LICENSE
dict_util-1.4.2.dist-info/METADATA
dict_util-1.4.2.dist-info/WHEEL
dict_util-1.4.2.dist-info/top_level.txt
dict_util-1.4.2.dist-info/RECORD
